[
  {
    "strDate": "2022-04-22",
    "strId": "11010",
    "strModDate": "2022-04-22",
    "strTarget": "_self",
    "strTitle": "本處蕭大使在「華盛頓郵報」(The Washington Post)於3月24日發表之專文",
    "strUrl": "/us/post/11010.html"
  },
  {
    "strDate": "2022-04-22",
    "strId": "11029",
    "strModDate": "2022-04-22",
    "strTarget": "_self",
    "strTitle": "本處蕭大使接受美「國家廣播公司」(NBC News)專訪於2月16日發佈",
    "strUrl": "/us/post/11029.html"
  },
  {
    "strDate": "2022-04-22",
    "strId": "11036",
    "strModDate": "2022-04-22",
    "strTarget": "_self",
    "strTitle": "本處蕭大使接受「日本經濟新聞」專訪於1月20日刊出",
    "strUrl": "/us/post/11036.html"
  },
  {
    "strDate": "2022-04-22",
    "strId": "11051",
    "strModDate": "2022-04-22",
    "strTarget": "_self",
    "strTitle": "本處蕭大使接受「路透社」（Reuters）專訪於2021年12月15日刊出",
    "strUrl": "/us/post/11051.html"
  },
  {
    "strDate": "2022-04-22",
    "strId": "11064",
    "strModDate": "2022-04-22",
    "strTarget": "_self",
    "strTitle": "本處蕭大使訪問夏威夷期間接受「檀香山星廣報」專訪於2021年9月3日刊出",
    "strUrl": "/us/post/11064.html"
  },
  {
    "strDate": "2022-04-22",
    "strId": "11073",
    "strModDate": "2022-04-22",
    "strTarget": "_self",
    "strTitle": "本處蕭大使接受芝加哥太陽報(Chicago Sun-Times)專訪於2021年10月3日刊出",
    "strUrl": "/us/post/11073.html"
  },
  {
    "strDate": "2022-04-22",
    "strId": "11078",
    "strModDate": "2022-04-22",
    "strTarget": "_self",
    "strTitle": "本處蕭大使接受印度TV9新聞台專訪於2021年9月23日播出",
    "strUrl": "/us/post/11078.html"
  },
  {
    "strDate": "2022-04-22",
    "strId": "11096",
    "strModDate": "2022-04-22",
    "strTarget": "_self",
    "strTitle": "本處蕭大使接受「政治報」(Politico)專訪於2021年9月9日刊出",
    "strUrl": "/us/post/11096.html"
  },
  {
    "strDate": "2022-04-22",
    "strId": "11099",
    "strModDate": "2022-04-22",
    "strTarget": "_self",
    "strTitle": "本處蕭大使應邀出席「全美議會交流理事會」 2021年7月28日至30日年會並發表專題演講",
    "strUrl": "/us/post/11099.html"
  },
  {
    "strDate": "2022-04-22",
    "strId": "11114",
    "strModDate": "2022-04-23",
    "strTarget": "_self",
    "strTitle": "本處蕭大使在《國家利益》(The National Interest)之專文於2021年5月19日刊登",
    "strUrl": "/us/post/11114.html"
  },
  {
    "strDate": "2022-04-22",
    "strId": "11118",
    "strModDate": "2022-04-22",
    "strTarget": "_self",
    "strTitle": "本處蕭大使接受日本「共同社」(Kyodo News)專訪於2021年2月16日刊出",
    "strUrl": "/us/post/11118.html"
  },
  {
    "strDate": "2022-04-22",
    "strId": "11122",
    "strModDate": "2022-04-22",
    "strTarget": "_self",
    "strTitle": "本處蕭大使在「國家利益」(National Interest)雜誌之專文於2020年10月8日刊登",
    "strUrl": "/us/post/11122.html"
  },
  {
    "strDate": "2022-04-23",
    "strId": "11151",
    "strModDate": "2022-04-23",
    "strTarget": "_self",
    "strTitle": "本處蕭大使在東亞日報之專訪於2021年8月3日刊登",
    "strUrl": "/us/post/11151.html"
  },
  {
    "strDate": "2022-04-25",
    "strId": "11237",
    "strModDate": "2022-04-26",
    "strTarget": "_self",
    "strTitle": "「外交家」（The Diplomat）網路雜誌2021年8月27日刊登外交部吳部長釗燮專文",
    "strUrl": "/us/post/11237.html"
  },
  {
    "strDate": "2022-04-25",
    "strId": "11240",
    "strModDate": "2022-04-26",
    "strTarget": "_self",
    "strTitle": "「外交家」（The Diplomat）網路雜誌2021年10月28日刊登行政院環保署張子敬署長專文",
    "strUrl": "/us/post/11240.html"
  },
  {
    "strDate": "2022-04-25",
    "strId": "11250",
    "strModDate": "2022-04-26",
    "strTarget": "_self",
    "strTitle": "「外交家」(The Diplomat)網路雜誌2021年5月4日刊登衛生福利部陳部長時中專文",
    "strUrl": "/us/post/11250.html"
  },
  {
    "strDate": "2022-04-25",
    "strId": "11255",
    "strModDate": "2022-04-26",
    "strTarget": "_self",
    "strTitle": "本處蕭大使在「外交家」網路雜誌(The Diplomat)之專訪於2021年2月11日刊登",
    "strUrl": "/us/post/11255.html"
  },
  {
    "strDate": "2022-04-30",
    "strId": "11398",
    "strModDate": "2022-04-30",
    "strTarget": "_self",
    "strTitle": "本處蕭大使接受「自由亞洲電台」(RFA)專訪於2022年4月28日刊出",
    "strUrl": "/us/post/11398.html"
  },
  {
    "strDate": "2022-05-17",
    "strId": "11578",
    "strModDate": "2022-05-17",
    "strTarget": "_self",
    "strTitle": "衛福部陳部長時中之「台灣如何成功抑制疫情」（How Taiwan successfully contained COVID）專文於5月13日在「華盛頓觀察家報」（The Washington Examiner）刊出",
    "strUrl": "/us/post/11578.html"
  },
  {
    "strDate": "2022-05-21",
    "strId": "11614",
    "strModDate": "2022-05-21",
    "strTarget": "_self",
    "strTitle": "本處蕭大使接受「政治報」(Politico) 專訪報導刊登",
    "strUrl": "/us/post/11614.html"
  },
  {
    "strDate": "2022-05-23",
    "strId": "11624",
    "strModDate": "2022-05-24",
    "strTarget": "_self",
    "strTitle": "蕭大使接受日本媒體富士電視台專訪",
    "strUrl": "/us/post/11624.html"
  },
  {
    "strDate": "2022-05-24",
    "strId": "11638",
    "strModDate": "2022-05-25",
    "strTarget": "_self",
    "strTitle": "吳部長接受「全美公共廣播電台」專訪",
    "strUrl": "/us/post/11638.html"
  },
  {
    "strDate": "2022-06-17",
    "strId": "11838",
    "strModDate": "2022-06-17",
    "strTarget": "_self",
    "strTitle": "吳部長接受「新聞頭條」電視新聞網專訪",
    "strUrl": "/us/post/11838.html"
  },
  {
    "strDate": "2022-06-17",
    "strId": "11851",
    "strModDate": "2022-06-17",
    "strTarget": "_self",
    "strTitle": "蕭大使接受聯邦眾議員Tim Burchett主持之Podcast訪談",
    "strUrl": "/us/post/11851.html"
  },
  {
    "strDate": "2022-06-25",
    "strId": "11887",
    "strModDate": "2022-07-16",
    "strTarget": "_self",
    "strTitle": "蕭大使接受美媒「華府外交家」(The Washington Diplomat)專訪於6月22日刊出",
    "strUrl": "/us/post/11887.html"
  },
  {
    "strDate": "2022-06-30",
    "strId": "11975",
    "strModDate": "2022-07-16",
    "strTarget": "_self",
    "strTitle": "國發會龔主委接受「華盛頓郵報」（The Washington Post）專訪",
    "strUrl": "/us/post/11975.html"
  },
  {
    "strDate": "2022-07-09",
    "strId": "12002",
    "strModDate": "2022-07-09",
    "strTarget": "_self",
    "strTitle": "行政院鄧振中政務委員接受「美國貿易內情」(Inside U.S. Trade)新聞網專訪(7月1日)",
    "strUrl": "/us/post/12002.html"
  },
  {
    "strDate": "2022-07-16",
    "strId": "12022",
    "strModDate": "2022-07-16",
    "strTarget": "_self",
    "strTitle": "行政院鄧振中政務委員接受「政治報」（Politico）專訪",
    "strUrl": "/us/post/12022.html"
  }
]